README.md
setup.py
goodlens_lib_product_scheme.egg-info/PKG-INFO
goodlens_lib_product_scheme.egg-info/SOURCES.txt
goodlens_lib_product_scheme.egg-info/dependency_links.txt
goodlens_lib_product_scheme.egg-info/requires.txt
goodlens_lib_product_scheme.egg-info/top_level.txt
goodlens_product/__init__.py
goodlens_product/util.py
goodlens_product/models/__init__.py
goodlens_product/models/base_model_.py
goodlens_product/models/create_product_common_response.py
goodlens_product/models/create_product_food_response.py
goodlens_product/models/food_origin_material.py
goodlens_product/models/food_origin_material_item.py
goodlens_product/models/food_origin_material_sub1.py
goodlens_product/models/food_origin_material_sub2.py
goodlens_product/models/food_origin_material_sub3.py
goodlens_product/models/food_origin_material_sub4.py
goodlens_product/models/food_origin_material_sub5.py
goodlens_product/models/nutrient.py
goodlens_product/models/nutrient_item.py
goodlens_product/models/nutrient_sub1.py
goodlens_product/models/nutrient_sub2.py
goodlens_product/models/product_common.py
goodlens_product/models/product_food.py
goodlens_product/models/update_product_common_response.py
goodlens_product/models/update_product_food_response.py