Metadata-Version: 1.0
Name: goodlens-lib-product-scheme
Version: 0.0.20
Summary: goodlens-lib-product-scheme
Home-page: UNKNOWN
Author: UNKNOWN
Author-email: UNKNOWN
License: UNKNOWN
Keywords: goodlens,goodlens-api,goodlens-lib-product-scheme
Platform: UNKNOWN
